interactive_pipe/__init__.py
interactive_pipe/core/__init__.py
interactive_pipe/core/cache.py
interactive_pipe/core/context.py
interactive_pipe/core/engine.py
interactive_pipe/core/filter.py
interactive_pipe/core/graph.py
interactive_pipe/core/pipeline.py
interactive_pipe/core/signature.py
interactive_pipe/data_objects/__init__.py
interactive_pipe/data_objects/audio.py
interactive_pipe/data_objects/curves.py
interactive_pipe/data_objects/data.py
interactive_pipe/data_objects/image.py
interactive_pipe/data_objects/parameters.py
interactive_pipe/graphical/__init__.py
interactive_pipe/graphical/gradio_control.py
interactive_pipe/graphical/gradio_gui.py
interactive_pipe/graphical/gui.py
interactive_pipe/graphical/mpl_control.py
interactive_pipe/graphical/mpl_gui.py
interactive_pipe/graphical/mpl_window.py
interactive_pipe/graphical/nb_control.py
interactive_pipe/graphical/nb_gui.py
interactive_pipe/graphical/qt_control.py
interactive_pipe/graphical/qt_gui.py
interactive_pipe/graphical/window.py
interactive_pipe/headless/__init__.py
interactive_pipe/headless/control.py
interactive_pipe/headless/keyboard.py
interactive_pipe/headless/pipeline.py
interactive_pipe/helper/__init__.py
interactive_pipe/helper/_private.py
interactive_pipe/helper/choose_backend.py
interactive_pipe/helper/control_abbreviation.py
interactive_pipe/helper/filter_decorator.py
interactive_pipe/helper/keyword_args_analyzer.py
interactive_pipe/helper/pipeline_decorator.py
interactive_pipe-0.8.8.dist-info/licenses/LICENSE
interactive_pipe-0.8.8.dist-info/METADATA
interactive_pipe-0.8.8.dist-info/WHEEL
interactive_pipe-0.8.8.dist-info/top_level.txt
interactive_pipe-0.8.8.dist-info/RECORD
