Metadata-Version: 2.4
Name: interactive_pipe
Version: 0.8.8
Summary: Library to create flexible interactive image processing pipelines and automatically add a graphical user interface without knowing anything about GUI coding!
Author-email: Balthazar Neveu <balthazarneveu@gmail.com>
Project-URL: Homepage, https://github.com/balthazarneveu/interactive_pipe
Project-URL: Bug Tracker, https://github.com/balthazarneveu/interactive_pipe/issues
Classifier: Programming Language :: Python :: 3
Classifier: License :: OSI Approved :: MIT License
Classifier: Operating System :: OS Independent
Requires-Python: >=3.7
License-File: LICENSE
Requires-Dist: matplotlib>=3.5.3
Requires-Dist: numpy>=1.21.6
Requires-Dist: Pillow>=9.0.1
Requires-Dist: PyYAML>=5.4.1
Requires-Dist: PyQt6>=6.5.2
Requires-Dist: PyQt6_sip>=13.5.2
Requires-Dist: opencv_python_headless>=4.8.1.78
Requires-Dist: pytest>=6.2.5
Requires-Dist: ipywidgets>=7.7.1
Requires-Dist: pandas
Requires-Dist: gradio
Provides-Extra: qt6
Requires-Dist: PyQt6>=6.5.2; extra == "qt6"
Requires-Dist: PyQt6_sip>=13.5.2; extra == "qt6"
Provides-Extra: qt5
Requires-Dist: PyQt5>=5.15.9; extra == "qt5"
Requires-Dist: PyQt5_sip>=12.12.1; extra == "qt5"
Provides-Extra: notebook
Requires-Dist: ipywidgets>=7.7.1; extra == "notebook"
Provides-Extra: pytest
Requires-Dist: opencv_python_headless>=4.8.1.78; extra == "pytest"
Requires-Dist: pytest>=6.2.5; extra == "pytest"
Provides-Extra: full
Requires-Dist: PyQt6>=6.5.2; extra == "full"
Requires-Dist: PyQt6_sip>=13.5.2; extra == "full"
Requires-Dist: opencv_python_headless>=4.8.1.78; extra == "full"
Requires-Dist: pytest>=6.2.5; extra == "full"
Requires-Dist: ipywidgets>=7.7.1; extra == "full"
Requires-Dist: pandas; extra == "full"
Requires-Dist: gradio; extra == "full"
Dynamic: license-file
